[{"class":"83722","date_posted":"2025-07-15 23:41:35 +0000 UTC","comment":"MPA Fundamentals of Public Admin. Incredibly caring, understanding, always making sure students feel supported. Lectures are insightful & engaging. Papers and exams were consistently fair, with clear instructions provided for every assignment. This clarity meant there was no reason for any student to struggle or fail if they followed her guidance.","difficulty_rating":1,"teacher_id":"UmF0aW5nLTQxNTAzNjQ0","clarity_rating":5,"student_grade":"A+","is_for_credit":true,"attendance_status":"mandatory","is_online":false,"comment_likes":0,"comment_dislikes":0,"rating_tags":"Amazing lectures --Caring--Respected","textbook_use":-1,"would_take_again":true},{"class":"83722","date_posted":"2025-04-18 13:24:20 +0000 UTC","comment":"10/10 amazing. One of the best at Kennesaw. Participation matters but she makes the lectures so easy going to where you would want to speak and give your opinion! Took her for fundamentals of Public Admin. ","difficulty_rating":2,"teacher_id":"UmF0aW5nLTQwOTc1NTU4","clarity_rating":5,"student_grade":"A+","is_for_credit":true,"attendance_status":"mandatory","is_online":false,"comment_likes":0,"comment_dislikes":0,"rating_tags":"Participation matters--Amazing lectures --Gives good feedback","textbook_use":3,"would_take_again":true}]