[{"class":"CS8260","date_posted":"2023-04-29 01:43:00 +0000 UTC","comment":"Thank you for being an exceptional instructor. I truly appreciate your supportive approach toward students. It's rare to find a professor like you who is simply amazing in every way! I wish all professors could demonstrate the same level of care toward their students. Once again, thank you for teaching us the advanced database course. ","difficulty_rating":1,"teacher_id":"UmF0aW5nLTM3NzU3Mzg1","clarity_rating":5,"student_grade":"A+","is_for_credit":true,"attendance_status":"non mandatory","is_online":false,"comment_likes":0,"comment_dislikes":0,"rating_tags":"Gives good feedback--Inspirational--Caring","textbook_use":3,"would_take_again":true}]