[{"class":"MOT420","date_posted":"2010-01-20 12:45:29 +0000 UTC","comment":"Prof. Sabbagh is a well educated and well informed. He teaches the class to one level and will allow you to catch up to understand the process and material. We need him Back as SPSU. Very approchable and a great teacher","difficulty_rating":3,"teacher_id":"UmF0aW5nLTE2NzM5MzA1","clarity_rating":5,"student_grade":"","is_for_credit":false,"attendance_status":"","is_online":false,"comment_likes":0,"comment_dislikes":0,"rating_tags":"","textbook_use":4,"would_take_again":true},{"class":"HIST101","date_posted":"2008-10-31 15:48:00 +0000 UTC","comment":"good","difficulty_rating":5,"teacher_id":"UmF0aW5nLTE0OTI0MTcx","clarity_rating":1,"student_grade":"","is_for_credit":false,"attendance_status":"","is_online":false,"comment_likes":0,"comment_dislikes":2,"rating_tags":"","textbook_use":1,"would_take_again":true},{"class":"MGNT1101","date_posted":"2007-01-10 14:25:00 +0000 UTC","comment":"Very good teacher. Test are not hard, only need to study the questions he gave you in class.","difficulty_rating":3,"teacher_id":"UmF0aW5nLTEyNzU0ODIx","clarity_rating":5,"student_grade":"","is_for_credit":false,"attendance_status":"","is_online":false,"comment_likes":1,"comment_dislikes":0,"rating_tags":"","textbook_use":5,"would_take_again":true},{"class":"MARKETINGPROJ","date_posted":"2005-10-05 22:05:25 +0000 UTC","comment":"He is a god of all teachers","difficulty_rating":2,"teacher_id":"UmF0aW5nLTEwNzQ0ODM4","clarity_rating":5,"student_grade":"","is_for_credit":false,"attendance_status":"","is_online":false,"comment_likes":1,"comment_dislikes":0,"rating_tags":"","textbook_use":null,"would_take_again":true},{"class":"PROJECTMGT","date_posted":"2005-08-30 23:06:17 +0000 UTC","comment":"speeds through material so that the whole class can get out early.  Subject matter is quite light so the pace he goes is perfect.  Hes funny and brings real world experience to each class","difficulty_rating":1,"teacher_id":"UmF0aW5nLTEwMjg2NjEy","clarity_rating":5,"student_grade":"B+","is_for_credit":false,"attendance_status":"Y","is_online":false,"comment_likes":1,"comment_dislikes":0,"rating_tags":"","textbook_use":null,"would_take_again":true},{"class":"PROJECTMGNT","date_posted":"2005-04-27 13:59:15 +0000 UTC","comment":"Cool professor.  Only bad thing is read from book powerpoint slides.","difficulty_rating":1,"teacher_id":"UmF0aW5nLTM3MjM3NTY=","clarity_rating":5,"student_grade":"","is_for_credit":false,"attendance_status":"","is_online":false,"comment_likes":0,"comment_dislikes":0,"rating_tags":"","textbook_use":null,"would_take_again":true}]