[{"class":"SPA400","date_posted":"2011-08-12 13:28:10 +0000 UTC","comment":"she is a VERY nice lady and willing to help in any way possible. Her classes however make no sense chronologically and you may be confused because she jumps around so much.Nice lady, a good contact to have if you are interested in a future in spanish or culture. GREAT person, but not a GREAT professor.","difficulty_rating":1,"teacher_id":"UmF0aW5nLTE4OTEwMTQy","clarity_rating":1,"student_grade":"","is_for_credit":false,"attendance_status":"","is_online":false,"comment_likes":0,"comment_dislikes":0,"rating_tags":"","textbook_use":1,"would_take_again":true}]